datahelp/__init__.py
datahelp/__version__.py
datahelp/create_project.py
datahelp/eda.py
datahelp/feature_engineering.py
datahelp/information.py
datahelp/modelling.py
datahelp/outlier.py
datahelp/timeseries.py
datahelp/utils.py
datahelp/visualize.py
datahelp/metrics/__init__.py
datahelp/metrics/classification.py
datahelp/metrics/regression.py
datahelp-1.0.0.dist-info/LICENSE.txt
datahelp-1.0.0.dist-info/METADATA
datahelp-1.0.0.dist-info/WHEEL
datahelp-1.0.0.dist-info/top_level.txt
datahelp-1.0.0.dist-info/RECORD
