Metadata-Version: 2.1
Name: datahelp
Version: 1.0.0
Summary: Data science library for data science / data analysis teams
Home-page: https://github.com/kimxons/datahelp
Author: Meshack Kitonga
Author-email: dev.kitonga@gmail.com
License: MIT
Classifier: Development Status :: 3 - Alpha
Classifier: License :: OSI Approved :: MIT License
Classifier: Intended Audience :: Developers
Classifier: Programming Language :: Python :: 3
Requires-Python: >=3.7
License-File: LICENSE.txt
Requires-Dist: pandas
Requires-Dist: scikit-learn
Requires-Dist: seaborn
Requires-Dist: numpy
Requires-Dist: jupyter
Requires-Dist: matplotlib
Requires-Dist: nltk
Requires-Dist: joblib
